contextextract/__init__.py
contextextract/cli.py
contextextract/extractor.py
contextextract/processors/__init__.py
contextextract/processors/pdf_processor.py
contextextract/processors/text_processor.py
contextextract/processors/url_processor.py
contextextract/utils/__init__.py
contextextract/utils/helpers.py
contextextract-0.1.0.dist-info/licenses/LICENSE.md
contextextract-0.1.0.dist-info/METADATA
contextextract-0.1.0.dist-info/WHEEL
contextextract-0.1.0.dist-info/entry_points.txt
contextextract-0.1.0.dist-info/top_level.txt
contextextract-0.1.0.dist-info/RECORD
