Metadata-Version: 2.4
Name: contextextract
Version: 0.1.0
Summary: Extract contextual key-value pairs from URLs, PDFs, or text using Groq API
Home-page: https://github.com/yourusername/contextextract
Author: SSJ
Author-email: SSJ <ssj@gmail.com>
License: MIT
Project-URL: Homepage, https://github.com/yourusername/contextextract
Project-URL: Bug Tracker, https://github.com/yourusername/contextextract/issues
Classifier: Programming Language :: Python :: 3
Classifier: License :: OSI Approved :: MIT License
Classifier: Operating System :: OS Independent
Requires-Python: >=3.8
License-File: LICENSE.md
Requires-Dist: requests>=2.25.0
Requires-Dist: beautifulsoup4>=4.9.0
Requires-Dist: PyPDF2>=2.0.0
Requires-Dist: tqdm>=4.60.0
Requires-Dist: groq>=0.4.0
Dynamic: author
Dynamic: home-page
Dynamic: license-file
Dynamic: requires-python
